latch_plots_helpers/__init__.py
latch_plots_helpers/plot_stats.py
latch_plots_helpers-0.1.2.dist-info/METADATA
latch_plots_helpers-0.1.2.dist-info/WHEEL
latch_plots_helpers-0.1.2.dist-info/licenses/LICENCE
latch_plots_helpers-0.1.2.dist-info/RECORD
